hireg_stats/__init__.py
hireg_stats/estimator.py
hireg_stats-0.1.9.dist-info/METADATA
hireg_stats-0.1.9.dist-info/WHEEL
hireg_stats-0.1.9.dist-info/top_level.txt
hireg_stats-0.1.9.dist-info/RECORD
